a8c_cusser/__init__.py
a8c_cusser/__main__.py
a8c_cusser/_misc.py
a8c_cusser/color_manager.py
a8c_cusser-0.2.0.dist-info/LICENSE
a8c_cusser-0.2.0.dist-info/METADATA
a8c_cusser-0.2.0.dist-info/WHEEL
a8c_cusser-0.2.0.dist-info/RECORD
