Metadata-Version: 2.1
Name: a8c-cusser
Version: 0.2.0
Summary: A curses wrapper that understands ANSI escape code sequences
Home-page: https://github.com/Automattic/cusser
License: MIT
Keywords: ansi-escape-codes,ansi,cli,command-line,console,cuia,curses,cusser,ncurses,pdcurses,terminal,tui
Author: Felipe S. S. Schneider
Author-email: schneider.felipe@posgrad.ufsc.br
Requires-Python: >=3.10,<4.0
Classifier: Development Status :: 4 - Beta
Classifier: Environment :: Console :: Curses
Classifier: Intended Audience :: Developers
Classifier: License :: OSI Approved :: MIT License
Classifier: Programming Language :: Python :: 3
Classifier: Programming Language :: Python :: 3.10
Classifier: Programming Language :: Python :: 3.11
Classifier: Programming Language :: Python :: 3.12
Classifier: Topic :: Software Development :: Libraries :: Python Modules
Classifier: Topic :: Software Development :: User Interfaces
Classifier: Topic :: Terminals :: Terminal Emulators/X Terminals
Classifier: Topic :: Text Processing :: Markup
Requires-Dist: stransi (>=0.3.0,<0.4.0)
Project-URL: Repository, https://github.com/Automattic/cusser
